fastapi_sa_orm_filter_2/__init__.py
fastapi_sa_orm_filter_2/main.py
fastapi_sa_orm_filter_2/operators.py
fastapi_sa_orm_filter_2/parsers.py
fastapi_sa_orm_filter_2-0.0.2.dist-info/LICENSE
fastapi_sa_orm_filter_2-0.0.2.dist-info/WHEEL
fastapi_sa_orm_filter_2-0.0.2.dist-info/METADATA
fastapi_sa_orm_filter_2-0.0.2.dist-info/RECORD
