Metadata-Version: 2.1
Name: fastapi-sa-orm-filter-2
Version: 0.0.2
Summary: FastAPI-SQLAlchemy filter, transform request query string to SQLAlchemy orm query
Author-email: Eric Richard <ehutzle@gmail.com>
Requires-Python: >=3.9
Classifier: License :: OSI Approved :: MIT License
Requires-Dist: fastapi
Requires-Dist: sqlalchemy
Requires-Dist: pydantic-sqlalchemy-2
Requires-Dist: flake8 ; extra == "formatting"
Requires-Dist: black ; extra == "formatting"
Requires-Dist: pytest ; extra == "test"
Requires-Dist: pytest-asyncio ; extra == "test"
Requires-Dist: aiosqlite ; extra == "test"
Project-URL: Home, https://github.com/ehutzle/sqlalchemy-fastapi-filters-2
Provides-Extra: formatting
Provides-Extra: test
